{
    "@context" : [
        "http://www.w3.org/ns/csvw",
        {
            "@language": "en"
        }
    ],
    "@type" : "TableGroup",
    "@id" : "https://example.org/university/data.csv-metadata.json",
    "tables" : [
        {
            "@id" : "https://example.org/university/data.csv-metadata.json",
            "@type" : "Table",
            "url" : "data-1.csv",
            "tableSchema" : {
                "@type" : "Schema",
                "aboutUrl": "http://newbase.com/{+universityIRI}",
                "columns" : [
                    {
                        "@type" : "Column",
                        "name" : "universityIRI",
                        "titles" : "universityIRI",
                        "dc:description" : "University ID",
                        "required" : true,
                        "datatype" : "string",
                        "propertyUrl": "http://example.org/vocabulary/entity",
                        "valueUrl": "http://example.org/vocabulary/{+universityIRI}"
                    },
                    {
                        "@type" : "Column",
                        "name" : "name",
                        "titles" : "name",
                        "dc:description" : "Name of the university",
                        "datatype" : "string",
                        "lang": "en",
                        "propertyUrl": "dcterms:title"
                    },
                    {
                        "@type" : "Column",
                        "name" : "ranking",
                        "titles" : "ranking",
                        "dc:description" : "Rank of the university",
                        "datatype" : "positiveInteger",
                        "propertyUrl": "https://dbpedia.org/ontology/ranking"
                    },
                    {
                        "@type" : "Column",
                        "name" : "address",
                        "titles" : "address",
                        "dc:description" : "Address of the university",
                        "datatype" : "string",
                        "lang": "cs",
                        "propertyUrl": "vcard:street-address"
                    },
                    {
                        "@type" : "Column",
                        "name" : "totalStudents",
                        "titles" : "totalStudents",
                        "dc:description" : "Number of students that study in the university",
                        "datatype" : "nonNegativeInteger",
                        "propertyUrl": "https://dbpedia.org/ontology/numberOfStudents"
                    },
                    {
                        "@type" : "Column",
                        "propertyUrl": "rdf:type",
                        "valueUrl": "http://vivoweb.org/ontology/core#University",
                        "virtual": true
                    }
                ],
                "primaryKey" : "universityIRI"
            }
        },

        {
            "@id" : "https://example.org/university/data.csv-metadata.json",
            "@type" : "Table",
            "url" : "data-2.csv",
            "tableSchema" : {
                "@type" : "Schema",
                "aboutUrl": "http://newbase.com/{+facultyIRI}",
                "columns" : [
                    {
                        "@type" : "Column",
                        "name" : "facultyIRI",
                        "titles" : "facultyIRI",
                        "dc:description" : "Faculty ID",
                        "required" : true,
                        "datatype" : "string",
                        "propertyUrl": "http://example.org/vocabulary/entity",
                        "valueUrl": "http://example.org/vocabulary/{+facultyIRI}"
                    },
                    {
                        "@type" : "Column",
                        "name" : "universityIRI",
                        "titles" : "universityIRI",
                        "dc:description" : "University ID",
                        "datatype" : "string",
                        "aboutUrl": "http://newbase.com/{+universityIRI}",
                        "propertyUrl": "http://example.org/vocabulary/constitutes",
                        "valueUrl": "http://newbase.com/{+facultyIRI}"
                    },
                    {
                        "@type" : "Column",
                        "name" : "name",
                        "titles" : "name",
                        "dc:description" : "Name of the faculty",
                        "datatype" : "string",
                        "lang": "en",
                        "propertyUrl": "dcterms:title"
                    },
                    {
                        "@type" : "Column",
                        "name" : "establishmentYear",
                        "titles" : "establishmentYear",
                        "dc:description" : "When the faculty was established",
                        "datatype" : "date",
                        "propertyUrl": "http://example.org/vocabulary/establishDate"
                    },
                    {
                        "@type" : "Column",
                        "name" : "budget",
                        "titles" : "budget",
                        "dc:description" : "budget of the faculty",
                        "datatype" : "double",
                        "propertyUrl": "https://dbpedia.org/ontology/budget"
                    },
                    {
                        "@type" : "Column",
                        "propertyUrl": "rdf:type",
                        "valueUrl": "http://purl.org/vocab/aiiso/schema#Faculty",
                        "virtual": true
                    },
                    {
                        "@type" : "Column",
                        "aboutUrl": "http://example.org/vocabulary/establishDate",
                        "propertyUrl": "rdf:type",
                        "valueUrl": "rdfs:Property",
                        "virtual": true
                    },
                    {
                        "@type" : "Column",
                        "datatype": "string",
                        "lang": "en",
                        "aboutUrl": "http://example.org/vocabulary/establishDate",
                        "propertyUrl": "rdfs:label",
                        "valueUrl": "xsd:string:establish_date",
                        "virtual": true
                    },
                    {
                        "@type" : "Column",
                        "aboutUrl": "http://example.org/vocabulary/establishDate",
                        "propertyUrl": "rdfs:comment",
                        "valueUrl": "xsd:string:date_when_something_was_established",
                        "virtual": true
                    },
                    {
                        "@type" : "Column",
                        "aboutUrl": "http://example.org/vocabulary/establishDate",
                        "propertyUrl": "rdfs:domain",
                        "valueUrl": "xsd:Faculty",
                        "virtual": true
                    },
                    {
                        "@type" : "Column",
                        "aboutUrl": "http://example.org/vocabulary/establishDate",
                        "propertyUrl": "rdfs:range",
                        "valueUrl": "xsd:date",
                        "virtual": true
                    },
                    {
                        "@type" : "Column",
                        "aboutUrl": "http://example.org/vocabulary/constitutes",
                        "propertyUrl": "rdf:type",
                        "valueUrl": "rdfs:Property",
                        "virtual": true
                    },
                    {
                        "@type" : "Column",
                        "aboutUrl": "http://example.org/vocabulary/constitutes",
                        "propertyUrl": "rdfs:label",
                        "valueUrl": "xsd:string:constitutes",
                        "virtual": true
                    },
                    {
                        "@type" : "Column",
                        "aboutUrl": "http://example.org/vocabulary/constitutes",
                        "propertyUrl": "rdfs:comment",
                        "valueUrl": "xsd:string:relates_university_and_faculty",
                        "virtual": true
                    },
                    {
                        "@type" : "Column",
                        "aboutUrl": "http://example.org/vocabulary/constitutes",
                        "propertyUrl": "rdfs:domain",
                        "valueUrl": "https://dbpedia.org/ontology/university",
                        "virtual": true
                    },
                    {
                        "@type" : "Column",
                        "aboutUrl": "http://example.org/vocabulary/constitutes",
                        "propertyUrl": "rdfs:range",
                        "valueUrl": "http://purl.org/vocab/aiiso/schema#Faculty",
                        "virtual": true
                    },
                    {
                    "@type" : "Column",
                    "aboutUrl": "http://example.org/vocabulary/establishDate",
                    "propertyUrl": "rdf:type",
                    "valueUrl": "rdfs:Property",
                    "virtual": true
                    }

                ],
                "primaryKey" : "facultyIRI",
                "foreignKeys" : [
                    {
                        "columnReference" : "universityIRI",
                        "reference" : {
                            "resource" : "data-1.csv",
                            "columnReference" : "universityIRI"
                        }
                    }
                ]
            }
        },


        {
            "@id" : "https://example.org/university/data.csv-metadata.json",
            "@type" : "Table",
            "url" : "data-3.csv",
            "tableSchema" : {
                "@type" : "Schema",
                "aboutUrl": "http://newbase.com/{+courseIRI}",
                "columns" : [
                    {
                        "@type" : "Column",
                        "name" : "courseIRI",
                        "titles" : "courseIRI",
                        "dc:description" : "Course IRI",
                        "required" : true,
                        "datatype" : "string",
                        "propertyUrl": "http://example.org/vocabulary/entity",
                        "valueUrl": "http://example.org/vocabulary/{+courseIRI}"
                    },
                    {
                        "@type" : "Column",
                        "name" : "courseID",
                        "titles" : "courseID",
                        "dc:description" : "Course ID",
                        "required" : true,
                        "datatype" : "string",
                        "lang": "en",
                        "propertyUrl": "http://schema.mobivoc.org/id"
                    },
                    {
                        "@type" : "Column",
                        "name" : "facultyIRI",
                        "titles" : "facultyIRI",
                        "dc:description" : "Faculty ID",
                        "datatype" : "string",
                        "aboutUrl": "http://newbase.com/{+facultyIRI}",
                        "propertyUrl": "http://example.org/vocabulary/teaches",
                        "valueUrl": "http://example.org/vocabulary/{+courseIRI}"
                    },
                    {
                        "@type" : "Column",
                        "name" : "totalCredits",
                        "titles" : "numberOfCredits",
                        "dc:description" : "Number of credits this course provides",
                        "datatype" : "nonNegativeInteger",
                        "propertyUrl": "http://example.org/vocabulary/numberOfCredits"
                    },
                    {
                        "@type" : "Column",
                        "name" : "totalCapacity",
                        "titles" : "maxCapacity",
                        "dc:description" : "Maximum students allowed to attend",
                        "datatype" : "nonNegativeInteger",
                        "propertyUrl": "http://example.org/vocabulary/capacity"
                    },
                    {
                        "@type" : "Column",
                        "propertyUrl": "rdf:type",
                        "valueUrl": "http://schema.mobivoc.org/Course",
                        "virtual": true
                    },
                    {
                        "@type" : "Column",
                        "aboutUrl": "http://example.org/vocabulary/teaches",
                        "propertyUrl": "rdf:type",
                        "valueUrl": "rdfs:Property",
                        "virtual": true
                    },
                    {
                        "@type" : "Column",
                        "datatype": "string",
                        "lang": "en",
                        "aboutUrl": "http://example.org/vocabulary/teaches",
                        "propertyUrl": "rdfs:label",
                        "valueUrl": "xsd:string:teaches",
                        "virtual": true
                    },
                    {
                        "@type" : "Column",
                        "aboutUrl": "http://example.org/vocabulary/teaches",
                        "propertyUrl": "rdfs:comment",
                        "valueUrl": "xsd:string:relatesfaculty_and_course",
                        "virtual": true
                    },
                    {
                        "@type" : "Column",
                        "aboutUrl": "http://example.org/vocabulary/teaches",
                        "propertyUrl": "rdfs:domain",
                        "valueUrl": "http://purl.org/vocab/aiiso/schema#Faculty",
                        "virtual": true
                    },
                    {
                        "@type" : "Column",
                        "aboutUrl": "http://example.org/vocabulary/teaches",
                        "propertyUrl": "rdfs:range",
                        "valueUrl": "http://schema.org/Course",
                        "virtual": true
                    }
                ],
                "primaryKey" : "courseIRI",
                "foreignKeys" : [
                    {
                        "columnReference" : "facultyIRI",
                        "reference" : {
                            "resource" : "data-2.csv",
                            "columnReference" : "facultyIRI"
                        }
                    }
                ]
            }
        },

        {
            "@id" : "https://example.org/university/data.csv-metadata.json",
            "@type" : "Table",
            "url" : "data-4.csv",
            "tableSchema" : {
                "@type" : "Schema",
                "aboutUrl": "http://newbase.com/{+universityIRI}",
                "columns" : [
                    {
                        "@type" : "Column",
                        "name" : "universityIRI",
                        "titles" : "universityIRI",
                        "dc:description" : "University ID",
                        "datatype" : "string",
                        "propertyUrl": "http://example.org/vocabulary/entity",
                        "valueUrl": "http://example.org/vocabulary/{+universityIRI}"
                    },
                    {
                        "@type" : "Column",
                        "name" : "phoneNumber",
                        "titles" : "phoneNumber",
                        "dc:description" : "Phone number of the university",
                        "datatype" : "string",
                        "lang": "en",
                        "propertyUrl": "http://open.vocab.org/terms/phoneNumber"
                    }
                ],
                "primaryKey" : "universityIRI",
                "foreignKeys" : [
                    {
                        "columnReference" : "universityIRI",
                        "reference" : {
                            "resource" : "data-1.csv",
                            "columnReference" : "universityIRI"
                        }
                    }
                ]
            }
        },

        {
            "@id" : "https://example.org/university/data.csv-metadata.json",
            "@type" : "Table",
            "url" : "data-5.csv",
            "tableSchema" : {
                "@type" : "Schema",
                "aboutUrl": "http://newbase.com/{+personIRI}",
                "columns" : [
                    {
                        "@type" : "Column",
                        "name" : "personIRI",
                        "titles" : "personIRI",
                        "dc:description" : "ID of the person",
                        "required" : true,
                        "datatype" : "string",
                        "propertyUrl": "http://example.org/vocabulary/entity",
                        "valueUrl": "http://example.org/vocabulary/{+personIRI}"
                    },
                    {
                        "@type" : "Column",
                        "name" : "universityIRI",
                        "titles" : "universityIRI",
                        "dc:description" : "University ID",
                        "datatype" : "string",
                        "propertyUrl": "http://example.org/vocabulary/isPartOf",
                        "valueUrl": "http://example.org/vocabulary/{+universityIRI}"
                    },
                    {
                        "@type" : "Column",
                        "aboutUrl": "http://example.org/vocabulary/isPartOf",
                        "propertyUrl": "rdf:type",
                        "valueUrl": "rdfs:Property",
                        "virtual": true
                    },
                    {
                        "@type" : "Column",
                        "datatype": "string",
                        "lang": "en",
                        "aboutUrl": "http://example.org/vocabulary/isPartOf",
                        "propertyUrl": "rdfs:number_of_people",
                        "valueUrl": "xsd:string:ispartof",
                        "virtual": true
                    },
                    {
                        "@type" : "Column",
                        "aboutUrl": "http://example.org/vocabulary/isPartOf",
                        "propertyUrl": "rdfs:comment",
                        "valueUrl": "xsd:string:relates_person_and_univesity",
                        "virtual": true
                    },
                    {
                        "@type" : "Column",
                        "aboutUrl": "http://example.org/vocabulary/isPartOf",
                        "propertyUrl": "rdfs:domain",
                        "valueUrl": "foaf:Person",
                        "virtual": true
                    },
                    {
                        "@type" : "Column",
                        "aboutUrl": "http://example.org/vocabulary/isPartOf",
                        "propertyUrl": "rdfs:range",
                        "valueUrl": "http://vivoweb.org/ontology/core#University",
                        "virtual": true
                    }
                ],
                "primaryKey" : "personIRI",
                "foreignKeys" : [
                    {
                        "columnReference" : "universityIRI",
                        "reference" : {
                            "resource" : "data-1.csv",
                            "columnReference" : "universityIRI"
                        }
                    }
                ]
            }
        },

        {
            "@id" : "https://example.org/university/data.csv-metadata.json",
            "@type" : "Table",
            "url" : "data-6.csv",
            "tableSchema" : {
                "@type" : "Schema",
                "aboutUrl": "http://newbase.com/{+personIRI}",
                "columns" : [
                    {
                        "@type" : "Column",
                        "name" : "personIRI",
                        "titles" : "personIRI",
                        "dc:description" : "ID of the person",
                        "required" : true,
                        "datatype" : "string",
                        "propertyUrl": "http://example.org/vocabulary/entity",
                        "valueUrl": "http://example.org/vocabulary/{+personIRI}"
                    },
                    {
                        "@type" : "Column",
                        "name" : "firstName",
                        "titles" : "firstName",
                        "dc:description" : "first name of the person",
                        "datatype" : "string",
                        "lang": "en",
                        "propertyUrl": "foaf:firstName"
                    },
                    {
                        "@type" : "Column",
                        "name" : "lastName",
                        "titles" : "lastName",
                        "dc:description" : "last name of the person",
                        "datatype" : "string",
                        "lang": "en",
                        "propertyUrl": "foaf:lastName"
                    },
                    {
                        "@type" : "Column",
                        "name" : "dataOfBirth",
                        "titles" : "dataOfBirth",
                        "dc:description" : "the date when a person was born",
                        "datatype" : "datetime",
                        "propertyUrl": "vcard:bday"
                    }
                ],
                "primaryKey" : "personIRI"
            }
        },

        {
            "@id" : "https://example.org/university/data.csv-metadata.json",
            "@type" : "Table",
            "url" : "data-7.csv",
            "tableSchema" : {
                "@type" : "Schema",
                "aboutUrl": "http://newbase.com/{+personIRI}",
                "columns" : [
                    {
                        "@type" : "Column",
                        "name" : "personIRI",
                        "titles" : "personIRI",
                        "dc:description" : "Person ID",
                        "datatype" : "string",
                        "propertyUrl": "http://example.org/vocabulary/entity",
                        "valueUrl": "http://example.org/vocabulary/{+personIRI}"
                    },
                    {
                        "@type" : "Column",
                        "name" : "phoneNumber",
                        "titles" : "phoneNumber",
                        "dc:description" : "Phone number of the university",
                        "datatype" : "string",
                        "lang": "en",
                        "propertyUrl": "http://open.vocab.org/terms/phoneNumber"
                    }
                ],
                "primaryKey" : "personIRI",
                "foreignKeys" : [
                    {
                        "columnReference" : "personIRI",
                        "reference" : {
                            "resource" : "data-5.csv",
                            "columnReference" : "personIRI"
                        }
                    }
                ]
            }
        },

        {
            "@id" : "https://example.org/university/data.csv-metadata.json",
            "@type" : "Table",
            "url" : "data-8.csv",
            "tableSchema" : {
                "@type" : "Schema",
                "aboutUrl": "http://newbase.com/{+personIRI}",
                "columns" : [
                    {
                        "@type" : "Column",
                        "name" : "personIRI",
                        "titles" : "personIRI",
                        "dc:description" : "Person ID",
                        "required" : true,
                        "datatype" : "string",
                        "propertyUrl": "http://example.org/vocabulary/entity",
                        "valueUrl": "http://example.org/vocabulary/{+personIRI}"
                    },
                    {
                        "@type" : "Column",
                        "name" : "programIRI",
                        "titles" : "programIRI",
                        "dc:description" : "study program that student is involved",
                        "datatype" : "string",
                        "propertyUrl": "http://example.org/vocabulary/studies",
                        "valueUrl": "http://newbase.com/{+programIRI}"
                    },
                    {
                        "@type" : "Column",
                        "name" : "yearOfStudy",
                        "titles" : "yearOfStudy",
                        "dc:description" : "year of the study at university",
                        "datatype" : "positiveInteger",
                        "propertyUrl": "http://example.org/vocabulary/yearOfStudy"
                    },
                    {
                        "@type" : "Column",
                        "name" : "gpa",
                        "titles" : "GPA",
                        "dc:description" : "GPA of the student",
                        "datatype" : "double",
                        "propertyUrl": "http://example.org/vocabulary/gpa"
                    },
                    {
                        "@type": "Column",
                        "propertyUrl": "rdf:type",
                        "valueUrl": "http://example.org/vocabulary/Student",
                        "virtual": true
                    },
                    {
                        "@type" : "Column",
                        "aboutUrl": "http://example.org/vocabulary/yearOfStudy",
                        "propertyUrl": "rdf:type",
                        "valueUrl": "rdfs:Property",
                        "virtual": true
                    },
                    {
                        "@type" : "Column",
                        "datatype": "string",
                        "lang": "en",
                        "aboutUrl": "http://example.org/vocabulary/yearOfStudy",
                        "propertyUrl": "rdfs:label",
                        "valueUrl": "xsd:string:yearofstudy",
                        "virtual": true
                    },
                    {
                        "@type" : "Column",
                        "aboutUrl": "http://example.org/vocabulary/yearOfStudy",
                        "propertyUrl": "rdfs:comment",
                        "valueUrl": "xsd:string:the_year_of_students_study",
                        "virtual": true
                    },
                    {
                        "@type" : "Column",
                        "aboutUrl": "http://example.org/vocabulary/yearOfStudy",
                        "propertyUrl": "rdfs:domain",
                        "valueUrl": "http://example.org/vocabulary/student",
                        "virtual": true
                    },
                    {
                        "@type" : "Column",
                        "aboutUrl": "http://example.org/vocabulary/yearOfStudy",
                        "propertyUrl": "rdfs:range",
                        "valueUrl": "xsd:positiveInteger",
                        "virtual": true
                    },
                    {
                        "@type" : "Column",
                        "aboutUrl": "http://example.org/vocabulary/gpa",
                        "propertyUrl": "rdf:type",
                        "valueUrl": "rdfs:Property",
                        "virtual": true
                    },
                    {
                        "@type" : "Column",
                        "datatype": "string",
                        "lang": "en",
                        "aboutUrl": "http://example.org/vocabulary/gpa",
                        "propertyUrl": "rdfs:label",
                        "valueUrl": "xsd:string:GPA",
                        "virtual": true
                    },
                    {
                        "@type" : "Column",
                        "aboutUrl": "http://example.org/vocabulary/gpa",
                        "propertyUrl": "rdfs:comment",
                        "valueUrl": "xsd:string:grade_point_average",
                        "virtual": true
                    },
                    {
                        "@type" : "Column",
                        "aboutUrl": "http://example.org/vocabulary/gpa",
                        "propertyUrl": "rdfs:domain",
                        "valueUrl": "http://example.org/vocabulary/student",
                        "virtual": true
                    },
                    {
                        "@type" : "Column",
                        "aboutUrl": "http://example.org/vocabulary/gpa",
                        "propertyUrl": "rdfs:range",
                        "valueUrl": "xsd:double",
                        "virtual": true
                    }

                ],
                "primaryKey" : "personIRI"
            }
        },

        {
            "@id" : "https://example.org/university/data.csv-metadata.json",
            "@type" : "Table",
            "url" : "data-9.csv",
            "tableSchema" : {
                "@type" : "Schema",
                "aboutUrl": "http://newbase.com/{+programIRI}",
                "columns" : [
                    {
                        "@type" : "Column",
                        "name" : "programIRI",
                        "titles" : "programIRI",
                        "dc:description" : "study program ID that student is involved",
                        "required" : true,
                        "datatype" : "string",
                        "propertyUrl": "http://example.org/vocabulary/entity",
                        "valueUrl": "http://example.org/vocabulary/{+programIRI}"
                    },
                    {
                        "@type" : "Column",
                        "name" : "name",
                        "titles" : "name",
                        "dc:description" : "name of the program",
                        "datatype" : "string",
                        "lang": "en",
                        "propertyUrl": "dcterms:title"
                    },
                    {
                        "@type" : "Column",
                        "name" : "totalStudents",
                        "titles" : "numberOfStudents",
                        "dc:description" : "number of students in the study program",
                        "datatype" : "nonNegativeInteger",
                        "propertyUrl": "https://dbpedia.org/ontology/numberOfStudents"
                    },
                    {
                        "@type": "Column",
                        "propertyUrl": "rdf:type",
                        "valueUrl": "http://schema.org/Course",
                        "virtual": true
                    }
                ],
                "primaryKey" : "programIRI"
            }
        },

        {
            "@id" : "https://example.org/university/data.csv-metadata.json",
            "@type" : "Table",
            "url" : "data-10.csv",
            "aboutUrl": "http://newbase.com/{+programIRI}",
            "tableSchema" : {
                "@type" : "Schema",
                "columns" : [
                    {
                        "@type" : "Column",
                        "name" : "programIRI",
                        "titles" : "programIRI",
                        "dc:description" : "study program ID that student is involved",
                        "datatype" : "string",
                        "propertyUrl": "http://example.org/vocabulary/entity",
                        "valueUrl": "http://example.org/vocabulary/{+programIRI}"
                    },
                    {
                        "@type" : "Column",
                        "name" : "courseList",
                        "titles" : "courseList",
                        "dc:description" : "list of courses",
                        "datatype" : "string",
                        "lang": "en",
                        "propertyUrl": "http://example.org/vocabulary/courseList"
                    }
                ],
                "primaryKey" : "programIRI",
                "foreignKeys" : [
                    {
                        "columnReference" : "programIRI",
                        "reference" : {
                            "resource" : "data-9.csv",
                            "columnReference" : "programIRI"
                        }
                    }
                ]
            }
        },

        {
            "@id" : "https://example.org/university/data.csv-metadata.json",
            "@type" : "Table",
            "url" : "data-12.csv",
            "aboutUrl": "http://newbase.com/{+personIRI}",
            "tableSchema" : {
                "@type" : "Schema",
                "columns" : [
                     {
                        "@type" : "Column",
                        "name" : "personIRI",
                        "titles" : "personIRI",
                        "dc:description" : "person ID",
                        "required" : true,
                        "datatype" : "string",
                        "propertyUrl": "http://example.org/vocabulary/entity",
                        "valueUrl": "http://example.org/vocabulary/{+personIRI}"
                    },
                    {
                        "@type" : "Column",
                        "name" : "officeHours",
                        "titles" : "officeHours",
                        "dc:description" : "office hours ID",
                        "required" : true,
                        "datatype" : "time",
                        "propertyUrl": "http://example.org/vocabulary/officeHours"
                    },
                    {
                        "@type" : "Column",
                        "aboutUrl": "http://example.org/vocabulary/officeHours",
                        "propertyUrl": "rdf:type",
                        "valueUrl": "rdfs:Property",
                        "virtual": true
                    },
                    {
                        "@type" : "Column",
                        "datatype": "string",
                        "lang": "en",
                        "aboutUrl": "http://example.org/vocabulary/officeHours",
                        "propertyUrl": "rdfs:label",
                        "valueUrl": "xsd:string:officehours",
                        "virtual": true
                    },
                    {
                        "@type" : "Column",
                        "aboutUrl": "http://example.org/vocabulary/officeHours",
                        "propertyUrl": "rdfs:comment",
                        "valueUrl": "xsd:string:time_and_date_when_the_office_is_open",
                        "virtual": true
                    },
                    {
                        "@type" : "Column",
                        "aboutUrl": "http://example.org/vocabulary/officeHours",
                        "propertyUrl": "rdfs:domain",
                        "valueUrl": "http://example.org/vocabulary/Professor",
                        "virtual": true
                    },
                    {
                        "@type" : "Column",
                        "aboutUrl": "http://example.org/vocabulary/officeHours",
                        "propertyUrl": "rdfs:range",
                        "valueUrl": "xsd:time",
                        "virtual": true
                    }

                ],
                "primaryKey" : "personIRI"
            }
        },

        {
            "@id" : "https://example.org/university/data.csv-metadata.json",
            "@type" : "Table",
            "url" : "data-13.csv",
            "aboutUrl": "http://newbase.com/{+personIRI}",
            "tableSchema" : {
                "@type" : "Schema",
                "columns" : [
                    {
                        "@type" : "Column",
                        "name" : "personIRI",
                        "titles" : "personIRI",
                        "dc:description" : "person ID",
                        "required" : true,
                        "datatype" : "string",
                        "propertyUrl": "http://example.org/vocabulary/entity",
                        "valueUrl": "http://example.org/vocabulary/{+personIRI}"
                    },
                    {
                        "@type" : "Column",
                        "name" : "researchIRI",
                        "titles" : "researchIRI",
                        "dc:description" : "research ID",
                        "required" : true,
                        "datatype" : "string",
                        "propertyUrl": "http://example.org/vocabulary/participatesIn"
                    },
                    {
                        "@type" : "Column",
                        "aboutUrl": "http://example.org/vocabulary/participatesIn",
                        "propertyUrl": "rdf:type",
                        "valueUrl": "rdfs:Property",
                        "virtual": true
                    },
                    {
                        "@type" : "Column",
                        "datatype": "string",
                        "lang": "en",
                        "aboutUrl": "http://example.org/vocabulary/participatesIn",
                        "propertyUrl": "rdfs:label",
                        "valueUrl": "xsd:string:participatesin",
                        "virtual": true
                    },
                    {
                        "@type" : "Column",
                        "aboutUrl": "http://example.org/vocabulary/participatesIn",
                        "propertyUrl": "rdfs:comment",
                        "valueUrl": "xsd:string:relates_professor_and_research",
                        "virtual": true
                    },
                    {
                        "@type" : "Column",
                        "aboutUrl": "http://example.org/vocabulary/participatesIn",
                        "propertyUrl": "rdfs:domain",
                        "valueUrl": "http://example.org/vocabulary/Person",
                        "virtual": true
                    },
                    {
                        "@type" : "Column",
                        "aboutUrl": "http://example.org/vocabulary/participatesIn",
                        "propertyUrl": "rdfs:range",
                        "valueUrl": "http://linkedscience.org/lsc/ns#Research",
                        "virtual": true
                    }
                ],
                "primaryKey" : [
                    "personIRI",
                    "researchIRI"  
                ],
                "foreignKeys" : [
                    {
                        "columnReference" : "researchIRI",
                        "reference" : {
                            "resource" : "data-14.csv",
                            "columnReference" : "researchIRI"
                        }
                    }
                ]
            }
        },

        {
            "@id" : "https://example.org/university/data.csv-metadata.json",
            "@type" : "Table",
            "url" : "data-14.csv",
            "tableSchema" : {
                "@type" : "Schema",
                "aboutUrl": "http://newbase.com/{+researchIRI}",
                "columns" : [
                    {
                        "@type" : "Column",
                        "name" : "researchIRI",
                        "titles" : "researchIRI",
                        "dc:description" : "research ID",
                        "required" : true,
                        "datatype" : "string",
                        "propertyUrl": "http://example.org/vocabulary/entity",
                        "valueUrl": "http://newbase.com/{+researchIRI}"

                    },
                    {
                        "@type" : "Column",
                        "name" : "name",
                        "titles" : "name",
                        "dc:description" : "research name",
                        "required" : true,
                        "datatype" : "string",
                        "lang": "en",
                        "propertyUrl": "dcterms:title"
                    },
                    {
                        "@type" : "Column",
                        "name" : "numberOfPeople",
                        "titles" : "numberOfPeople",
                        "dc:description" : "Number of people involved in research",
                        "required" : true,
                        "datatype" : "positiveInteger",
                        "propertyUrl": "http://example.org/vocabulary/numberOfPeopleInResearch"
                    },
                    {
                        "@type" : "Column",
                        "name" : "startDate",
                        "titles" : "startDate",
                        "dc:description" : "Start date of research",
                        "required" : true,
                        "datatype" : "date",
                        "propertyUrl": "http://rdf-vocabulary.ddialliance.org/discovery#startDate"
                    },
                    {
                        "@type": "Column",
                        "propertyUrl": "rdf:type",
                        "valueUrl": "http://linkedscience.org/lsc/ns#Research",
                        "virtual": true
                    },
                    {
                        "@type" : "Column",
                        "aboutUrl": "http://example.org/vocabulary/numberOfPeopleInResearch",
                        "propertyUrl": "rdf:type",
                        "valueUrl": "rdfs:Property",
                        "virtual": true
                    },
                    {
                        "@type" : "Column",
                        "datatype": "string",
                        "lang": "en",
                        "aboutUrl": "http://example.org/vocabulary/numberOfPeopleInResearch",
                        "propertyUrl": "rdfs:label",
                        "valueUrl": "xsd:string:teaches",
                        "virtual": true
                    },
                    {
                        "@type" : "Column",
                        "aboutUrl": "http://example.org/vocabulary/numberOfPeopleInResearch",
                        "propertyUrl": "rdfs:comment",
                        "valueUrl": "xsd:string:relatesnumber_of_people_involved_in_some_scientific_research",
                        "virtual": true
                    },
                    {
                        "@type" : "Column",
                        "aboutUrl": "http://example.org/vocabulary/numberOfPeopleInResearch",
                        "propertyUrl": "rdfs:domain",
                        "valueUrl": "http://example.org/vocabulary/Research",
                        "virtual": true
                    },
                    {
                        "@type" : "Column",
                        "aboutUrl": "http://example.org/vocabulary/numberOfPeopleInResearch",
                        "propertyUrl": "rdfs:range",
                        "valueUrl": "xsd:positiveInteger",
                        "virtual": true
                    }
                ],
                "primaryKey" : "researchIRI"
            }
        },

        
        {
            "@id" : "https://example.org/university/data.csv-metadata.json",
            "@type" : "Table",
            "url" : "data-15.csv",
            "tableSchema" : {
                "@type" : "Schema",
                "aboutUrl": "http://newbase.com/{+paperIRI}",
                "columns" : [
                    {
                        "@type" : "Column",
                        "name" : "paperIRI",
                        "titles" : "paperIRI",
                        "dc:description" : "paper ID",
                        "required" : true,
                        "datatype" : "string",
                        "propertyUrl": "http://example.org/vocabulary/entity",
                        "valueUrl": "http://newbase.com/{+paperIRI}"
                    },
                    {
                        "@type" : "Column",
                        "name" : "name",
                        "titles" : "name",
                        "dc:description" : "paper name",
                        "required" : true,
                        "datatype" : "string",
                        "lang":"en",
                        "propertyUrl": "dcterms:title"
                    },
                    {
                        "@type" : "Column",
                        "name" : "numberOfPeople",
                        "titles" : "numberOfPeople",
                        "dc:description" : "Number of people involved in paper",
                        "required" : true,
                        "datatype" : "positiveInteger",
                        "propertyUrl": "http://example.org/vocabulary/numberOfPeopleInPaper"
                    },
                    {
                        "@type" : "Column",
                        "name" : "startDate",
                        "titles" : "startDate",
                        "dc:description" : "Start date of research",
                        "required" : true,
                        "datatype" : "date",
                        "propertyUrl": "http://rdf-vocabulary.ddialliance.org/discovery#startDate"
                    },
                    {
                        "@type": "Column",
                        "propertyUrl": "rdf:type",
                        "valueUrl": "http://example.org/vocabulary/Paper",
                        "virtual": true
                    },
                    {
                        "@type" : "Column",
                        "aboutUrl": "http://example.org/vocabulary/numberOfPeopleInPaper",
                        "propertyUrl": "rdf:type",
                        "valueUrl": "rdfs:Property",
                        "virtual": true
                    },
                    {
                        "@type" : "Column",
                        "datatype": "string",
                        "lang": "en",
                        "aboutUrl": "http://example.org/vocabulary/numberOfPeopleInPaper",
                        "propertyUrl": "rdfs:number_of_people",
                        "valueUrl": "xsd:string:teaches",
                        "virtual": true
                    },
                    {
                        "@type" : "Column",
                        "aboutUrl": "http://example.org/vocabulary/numberOfPeopleInPaper",
                        "propertyUrl": "rdfs:comment",
                        "valueUrl": "xsd:string:relatesnumber_of_people_involved_in_some_scientific_paper",
                        "virtual": true
                    },
                    {
                        "@type" : "Column",
                        "aboutUrl": "http://example.org/vocabulary/numberOfPeopleInPaper",
                        "propertyUrl": "rdfs:domain",
                        "valueUrl": "http://example.org/vocabulary/Paper",
                        "virtual": true
                    },
                    {
                        "@type" : "Column",
                        "aboutUrl": "http://example.org/vocabulary/numberOfPeopleInPaper",
                        "propertyUrl": "rdfs:range",
                        "valueUrl": "xsd:positiveInteger",
                        "virtual": true
                    }

                ],
                "primaryKey" : "paperIRI"
            }
        },

        {
            "@id" : "https://example.org/university/data.csv-metadata.json",
            "@type" : "Table",
            "url" : "data-16.csv",
            "aboutUrl": "http://newbase.com/{+personIRI}",
            "tableSchema" : {
                "@type" : "Schema",
                "columns" : [
                    {
                        "@type" : "Column",
                        "name" : "personIRI",
                        "titles" : "personIRI",
                        "dc:description" : "person ID",
                        "required" : true,
                        "datatype" : "string",
                        "propertyUrl": "http://example.org/vocabulary/entity",
                        "valueUrl": "http://example.org/vocabulary/{+personIRI}"
                    },
                    {
                        "@type" : "Column",
                        "name" : "paperIRI",
                        "titles" : "paperIRI",
                        "dc:description" : "paper ID",
                        "required" : true,
                        "datatype" : "string",
                        "propertyUrl": "http://example.org/vocabulary/isAuthorOf"
                    },
                    {
                        "@type" : "Column",
                        "aboutUrl": "http://example.org/vocabulary/isAuthorOf",
                        "propertyUrl": "rdf:type",
                        "valueUrl": "rdfs:Property",
                        "virtual": true
                    },
                    {
                        "@type" : "Column",
                        "datatype": "string",
                        "lang": "en",
                        "aboutUrl": "http://example.org/vocabulary/isAuthorOf",
                        "propertyUrl": "rdfs:label",
                        "valueUrl": "xsd:string:isauthorof",
                        "virtual": true
                    },
                    {
                        "@type" : "Column",
                        "aboutUrl": "http://example.org/vocabulary/isAuthorOf",
                        "propertyUrl": "rdfs:comment",
                        "valueUrl": "xsd:string:relates_professor_and_paper",
                        "virtual": true
                    },
                    {
                        "@type" : "Column",
                        "aboutUrl": "http://example.org/vocabulary/isAuthorOf",
                        "propertyUrl": "rdfs:domain",
                        "valueUrl": "http://example.org/vocabulary/Professor",
                        "virtual": true
                    },
                    {
                        "@type" : "Column",
                        "aboutUrl": "http://example.org/vocabulary/isAuthorOf",
                        "propertyUrl": "rdfs:range",
                        "valueUrl": "http://example.org/vocabulary/Paper",
                        "virtual": true
                    }
                    
                ],
                "primaryKey" : [
                    "personIRI",
                    "paperIRI"
                ],
                "foreignKeys" : [
                    {
                        "columnReference" : "paperIRI",
                        "reference" : {
                            "resource" : "data-15.csv",
                            "columnReference" : "paperIRI"
                        }
                    }
                ]
            }
        }

    ]
}